happycode/__init__.py
happycode-0.0.1.dist-info/LICENSE
happycode-0.0.1.dist-info/METADATA
happycode-0.0.1.dist-info/WHEEL
happycode-0.0.1.dist-info/top_level.txt
happycode-0.0.1.dist-info/RECORD
