Metadata-Version: 2.1
Name: happycode
Version: 0.0.1
Summary: HappyCode is Shabi!!!
Home-page: https://www.luogu.com.cn/user/546369
Author: HappyCode Shabi
Author-email: happycode@shabi.com
Classifier: Programming Language :: Python :: 3
Classifier: License :: OSI Approved :: MIT License
Classifier: Operating System :: OS Independent
License-File: LICENSE
